<?xml version="1.0" encoding="utf-8" ?>
<dwsync>
<file name="HoaDinh-pressurecook-0921.jpg" server="C:/xampp/htdocs/PressureCooker/" local="131818040460000000" remote="131818004460000000" Dst="2" />
<file name="HoaDinh-pressurecook-0948.jpg" server="C:/xampp/htdocs/PressureCooker/" local="131818040460000000" remote="131818004460000000" Dst="2" />
<file name="HoaDinh-pressurecook-0974.jpg" server="C:/xampp/htdocs/PressureCooker/" local="131818040460000000" remote="131818004460000000" Dst="2" />
<file name="HoaDinh-pressurecook-1022.jpg" server="C:/xampp/htdocs/PressureCooker/" local="131818040480000000" remote="131818004480000000" Dst="2" />
<file name="HoaDinh-pressurecook-1043.jpg" server="C:/xampp/htdocs/PressureCooker/" local="131818040480000000" remote="131818004480000000" Dst="2" />
<file name="IP_ChrisFernance_PC_1.jpg" server="C:/xampp/htdocs/PressureCooker/" local="131811865860000000" remote="131811829860000000" Dst="2" />
<file name="IP_ChrisFernance_PC_2.jpg" server="C:/xampp/htdocs/PressureCooker/" local="131811866600000000" remote="131811830600000000" Dst="2" />
<file name="IP_ChrisFernance_PC_4.jpg" server="C:/xampp/htdocs/PressureCooker/" local="131811866980000000" remote="131811830980000000" Dst="2" />
<file name="IP_ChrisFernance_PC_7.jpg" server="C:/xampp/htdocs/PressureCooker/" local="131811867460000000" remote="131811831460000000" Dst="2" />
<file name="IP_ChrisFernance_PC_8.jpg" server="C:/xampp/htdocs/PressureCooker/" local="131811867720000000" remote="131811831720000000" Dst="2" />
<file name="Maria Koulouris_Pressure Cooker-10.jpg" server="C:/xampp/htdocs/PressureCooker/" local="131817952500000000" remote="131817916500000000" Dst="2" />
<file name="Maria Koulouris_Pressure Cooker-12.jpg" server="C:/xampp/htdocs/PressureCooker/" local="131817952520000000" remote="131817916520000000" Dst="2" />
<file name="Maria Koulouris_Pressure Cooker-13.jpg" server="C:/xampp/htdocs/PressureCooker/" local="131817952540000000" remote="131817916540000000" Dst="2" />
<file name="Maria Koulouris_Pressure Cooker-14.jpg" server="C:/xampp/htdocs/PressureCooker/" local="131817952560000000" remote="131817916560000000" Dst="2" />
<file name="Maria Koulouris_Pressure Cooker-15.jpg" server="C:/xampp/htdocs/PressureCooker/" local="131817952560000000" remote="131817916560000000" Dst="2" />
<file name="Maria Koulouris_Pressure Cooker-16.jpg" server="C:/xampp/htdocs/PressureCooker/" local="131817952580000000" remote="131817916580000000" Dst="2" />
<file name="Maria Koulouris_Pressure Cooker-2.jpg" server="C:/xampp/htdocs/PressureCooker/" local="131817952400000000" remote="131817916400000000" Dst="2" />
<file name="Maria Koulouris_Pressure Cooker-4.jpg" server="C:/xampp/htdocs/PressureCooker/" local="131817952400000000" remote="131817916400000000" Dst="2" />
<file name="Maria Koulouris_Pressure Cooker-6.jpg" server="C:/xampp/htdocs/PressureCooker/" local="131817952460000000" remote="131817916460000000" Dst="2" />
<file name="Maria Koulouris_Pressure Cooker-8.jpg" server="C:/xampp/htdocs/PressureCooker/" local="131817952440000000" remote="131817916440000000" Dst="2" />
</dwsync>